tuxlava/__init__.py
tuxlava/__main__.py
tuxlava/argparse.py
tuxlava/exceptions.py
tuxlava/jobs.py
tuxlava/requests.py
tuxlava/tuxmake.py
tuxlava/utils.py
tuxlava/devices/__init__.py
tuxlava/devices/avh.py
tuxlava/devices/fastboot.py
tuxlava/devices/flasher.py
tuxlava/devices/fvp.py
tuxlava/devices/nfs.py
tuxlava/devices/qemu.py
tuxlava/devices/ssh.py
tuxlava/templates/__init__.py
tuxlava/templates/devices/avh.yaml.jinja2
tuxlava/templates/devices/base.yaml.jinja2
tuxlava/templates/devices/fastboot.yaml.jinja2
tuxlava/templates/devices/fvp.yaml.jinja2
tuxlava/templates/devices/nfs.yaml.jinja2
tuxlava/templates/devices/qemu.yaml.jinja2
tuxlava/templates/devices/ssh.yaml.jinja2
tuxlava/templates/jobs/avh.yaml.jinja2
tuxlava/templates/jobs/fastboot-aosp.yaml.jinja2
tuxlava/templates/jobs/fastboot-oe.yaml.jinja2
tuxlava/templates/jobs/fastboot.yaml.jinja2
tuxlava/templates/jobs/flasher-debian.yaml.jinja2
tuxlava/templates/jobs/flasher-poky-altcfg.yaml.jinja2
tuxlava/templates/jobs/flasher-qcom-distro.yaml.jinja2
tuxlava/templates/jobs/flasher.yaml.jinja2
tuxlava/templates/jobs/fvp-aemva.yaml.jinja2
tuxlava/templates/jobs/fvp-morello.yaml.jinja2
tuxlava/templates/jobs/nfs.yaml.jinja2
tuxlava/templates/jobs/qemu.yaml.jinja2
tuxlava/templates/jobs/ssh.yaml.jinja2
tuxlava/templates/tests/android-xts.yaml.jinja2
tuxlava/templates/tests/commands.yaml.jinja2
tuxlava/templates/tests/fwts.yaml.jinja2
tuxlava/templates/tests/hackingsession.yaml.jinja2
tuxlava/templates/tests/kselftest.yaml.jinja2
tuxlava/templates/tests/kunit.yaml.jinja2
tuxlava/templates/tests/kvm-unit-tests.yaml.jinja2
tuxlava/templates/tests/libgpiod.yaml.jinja2
tuxlava/templates/tests/libhugetlbfs.yaml.jinja2
tuxlava/templates/tests/ltp.yaml.jinja2
tuxlava/templates/tests/mmtests.yaml.jinja2
tuxlava/templates/tests/modules.yaml.jinja2
tuxlava/templates/tests/morello-busybox-acpi.yaml.jinja2
tuxlava/templates/tests/morello-busybox-dt.yaml.jinja2
tuxlava/templates/tests/morello-busybox-purecap.yaml.jinja2
tuxlava-0.10.3.dist-info/entry_points.txt
tuxlava-0.10.3.dist-info/licenses/LICENSE
tuxlava-0.10.3.dist-info/WHEEL
tuxlava-0.10.3.dist-info/METADATA
tuxlava-0.10.3.dist-info/RECORD
