Metadata-Version: 2.4
Name: tuxlava
Version: 0.10.3
Summary: Python library and command line tool for generating LAVA jobs
Home-page: https://tuxlava.org/
Author: Senthil Kumaran
Author-email: senthil.kumaran@linaro.org
Requires-Python: >=3.9
Classifier: License :: OSI Approved :: MIT License
License-File: LICENSE
Requires-Dist: jinja2
Requires-Dist: requests
Requires-Dist: PyYAML
